mmindexer/__init__.py
mmindexer/index.py
mmindexer/scan.py
music_metadata_indexer-0.0.2.dist-info/LICENSE
music_metadata_indexer-0.0.2.dist-info/METADATA
music_metadata_indexer-0.0.2.dist-info/WHEEL
music_metadata_indexer-0.0.2.dist-info/top_level.txt
music_metadata_indexer-0.0.2.dist-info/RECORD
